Metadata-Version: 2.1
Name: pyzerox-impacte
Version: 0.0.8
Summary: ocr documents using vision models from all popular providers like OpenAI, Azure OpenAI, Anthropic, AWS Bedrock etc
Home-page: https://github.com/getomni-ai/zerox.git
License: MIT
Keywords: ocr,document,llm
Author: wizenheimer
Requires-Python: >=3.11,<4.0
Classifier: License :: OSI Approved :: MIT License
Classifier: Programming Language :: Python :: 3
Classifier: Programming Language :: Python :: 3.11
Classifier: Programming Language :: Python :: 3.12
Classifier: Programming Language :: Python :: 3.13
Requires-Dist: aiofiles (>=23.0,<24.0)
Requires-Dist: aiohttp (>=3.9.5,<4.0.0)
Requires-Dist: aioshutil (>=1.5,<2.0)
Requires-Dist: litellm (>=1.44.15,<2.0.0)
Requires-Dist: pdf2image (>=1.17.0,<2.0.0)
Requires-Dist: pypdf2 (>=3.0.1,<4.0.0)
Project-URL: Documentation, https://github.com/getomni-ai/zerox
Project-URL: Repository, https://github.com/getomni-ai/zerox.git
